pjscan/__init__.py
pjscan/analysis_framework.py
pjscan/const.py
pjscan/exceptions.py
pjscan/graph_traversal.py
pjscan/graph_traversal_recorder.py
pjscan/helper.py
pjscan/neo4j_defauilt_config.py
pjscan/cache/__init__.py
pjscan/cache/cache_graph.py
pjscan/cache/prefetch_task.py
pjscan/cache/prefetch_thread.py
pjscan/cache/thread_pool.py
pjscan/steps/__init__.py
pjscan/steps/abstract_step.py
pjscan/steps/ast_step.py
pjscan/steps/basic_step.py
pjscan/steps/cfg_step.py
pjscan/steps/cg_step.py
pjscan/steps/chg_step.py
pjscan/steps/code_step.py
pjscan/steps/fig_step.py
pjscan/steps/pdg_step.py
pjscan/steps/range_step.py
pjscan-1.0.2.dist-info/AUTHORS.txt
pjscan-1.0.2.dist-info/LICENSE.txt
pjscan-1.0.2.dist-info/METADATA
pjscan-1.0.2.dist-info/WHEEL
pjscan-1.0.2.dist-info/top_level.txt
pjscan-1.0.2.dist-info/zip-safe
pjscan-1.0.2.dist-info/RECORD
