Metadata-Version: 2.1
Name: pjscan
Version: 1.0.2
Summary: Analysis framework for PHPJoy 
Home-page: https://github.com/EnhancedPHPJoern/PJScan
Author: shaobaobaoer
Author-email: shaobaobaoer@126.com
License: New BSD
Keywords: click plugin setuptools entry-point
Platform: UNKNOWN
Classifier: Topic :: Utilities
Classifier: Intended Audience :: Developers
Classifier: Development Status :: 5 - Production/Stable
Classifier: License :: OSI Approved :: BSD License
Classifier: Programming Language :: Python
Classifier: Programming Language :: Python :: 3
License-File: LICENSE.txt
License-File: AUTHORS.txt
Requires-Dist: py2neo
Requires-Dist: networkx
Requires-Dist: Levenshtein
Requires-Dist: pandas
Requires-Dist: ruamel.yaml
